{"trial_id": "0379", "hyperparameters": {"space": [{"class_name": "Int", "config": {"name": "num_nodes", "default": null, "conditions": [], "min_value": 15, "max_value": 150, "step": 5, "sampling": "linear"}}, {"class_name": "Int", "config": {"name": "num_layers", "default": null, "conditions": [], "min_value": 2, "max_value": 5, "step": 1, "sampling": "linear"}}, {"class_name": "Boolean", "config": {"name": "dropout", "default": false, "conditions": []}}, {"class_name": "Choice", "config": {"name": "activation", "default": "relu", "conditions": [], "values": ["relu", "tanh", "sigmoid"], "ordered": false}}, {"class_name": "Choice", "config": {"name": "learning_rate", "default": 0.1, "conditions": [], "values": [0.1, 0.01, 0.001], "ordered": true}}, {"class_name": "Choice", "config": {"name": "optimizer", "default": "adam", "conditions": [], "values": ["adam", "SGD", "rmsprop"], "ordered": false}}, {"class_name": "Choice", "config": {"name": "batch_size", "default": 32, "conditions": [], "values": [32, 64, 128], "ordered": true}}], "values": {"num_nodes": 135, "num_layers": 2, "dropout": true, "activation": "sigmoid", "learning_rate": 0.01, "optimizer": "rmsprop", "batch_size": 64, "tuner/epochs": 2, "tuner/initial_epoch": 0, "tuner/bracket": 6, "tuner/round": 0}}, "metrics": {"metrics": {"loss": {"direction": "min", "observations": [{"value": [0.6007513999938965], "step": 1}]}, "mean_squared_error": {"direction": "min", "observations": [{"value": [0.6007513999938965], "step": 1}]}, "mean_absolute_error": {"direction": "min", "observations": [{"value": [0.14966826140880585], "step": 1}]}, "mean_absolute_percentage_error": {"direction": "min", "observations": [{"value": [288.3220520019531], "step": 1}]}, "val_loss": {"direction": "min", "observations": [{"value": [0.4934699833393097], "step": 1}]}, "val_mean_squared_error": {"direction": "min", "observations": [{"value": [0.4934699833393097], "step": 1}]}, "val_mean_absolute_error": {"direction": "min", "observations": [{"value": [0.13598522543907166], "step": 1}]}, "val_mean_absolute_percentage_error": {"direction": "min", "observations": [{"value": [243.68714904785156], "step": 1}]}, "lr": {"direction": "min", "observations": [{"value": [0.009999999776482582], "step": 1}]}}}, "score": 0.4934699833393097, "best_step": 1, "status": "COMPLETED", "message": null}