{"trial_id": "1495", "hyperparameters": {"space": [{"class_name": "Int", "config": {"name": "num_nodes", "default": null, "conditions": [], "min_value": 15, "max_value": 150, "step": 5, "sampling": "linear"}}, {"class_name": "Int", "config": {"name": "num_layers", "default": null, "conditions": [], "min_value": 2, "max_value": 5, "step": 1, "sampling": "linear"}}, {"class_name": "Boolean", "config": {"name": "dropout", "default": false, "conditions": []}}, {"class_name": "Choice", "config": {"name": "activation", "default": "relu", "conditions": [], "values": ["relu", "tanh", "sigmoid"], "ordered": false}}, {"class_name": "Choice", "config": {"name": "learning_rate", "default": 0.1, "conditions": [], "values": [0.1, 0.01, 0.001], "ordered": true}}, {"class_name": "Choice", "config": {"name": "optimizer", "default": "adam", "conditions": [], "values": ["adam", "SGD", "rmsprop"], "ordered": false}}, {"class_name": "Choice", "config": {"name": "batch_size", "default": 32, "conditions": [], "values": [32, 64, 128], "ordered": true}}], "values": {"num_nodes": 150, "num_layers": 2, "dropout": false, "activation": "relu", "learning_rate": 0.001, "optimizer": "rmsprop", "batch_size": 64, "tuner/epochs": 13, "tuner/initial_epoch": 5, "tuner/bracket": 5, "tuner/round": 1, "tuner/trial_id": "1433"}}, "metrics": {"metrics": {"loss": {"direction": "min", "observations": [{"value": [0.15391455590724945], "step": 6}]}, "mean_squared_error": {"direction": "min", "observations": [{"value": [0.15391455590724945], "step": 6}]}, "mean_absolute_error": {"direction": "min", "observations": [{"value": [0.09653957188129425], "step": 6}]}, "mean_absolute_percentage_error": {"direction": "min", "observations": [{"value": [284.6651916503906], "step": 6}]}, "val_loss": {"direction": "min", "observations": [{"value": [0.26368585228919983], "step": 6}]}, "val_mean_squared_error": {"direction": "min", "observations": [{"value": [0.26368585228919983], "step": 6}]}, "val_mean_absolute_error": {"direction": "min", "observations": [{"value": [0.09106221050024033], "step": 6}]}, "val_mean_absolute_percentage_error": {"direction": "min", "observations": [{"value": [288.4572448730469], "step": 6}]}, "lr": {"direction": "min", "observations": [{"value": [0.0010000000474974513], "step": 6}]}}}, "score": 0.26368585228919983, "best_step": 6, "status": "COMPLETED", "message": null}